pccc/__init__.py
pccc/config.py
pccc/exceptions.py
pccc/factories.py
pccc/parser.py
pccc-0.4.14.dist-info/LICENSE.rst
pccc-0.4.14.dist-info/METADATA
pccc-0.4.14.dist-info/WHEEL
pccc-0.4.14.dist-info/entry_points.txt
pccc-0.4.14.dist-info/top_level.txt
pccc-0.4.14.dist-info/RECORD
