Metadata-Version: 2.1
Name: pccc
Version: 0.4.14
Summary: Python Conventional Commit Checker
Home-page: https://github.com/jeremyagray/pccc
Author: Jeremy A Gray
Author-email: gray@flyquackswim.com
Maintainer: Jeremy A Gray
Maintainer-email: gray@flyquackswim.com
License: GPL-3.0-or-later
Project-URL: Issues, https://github.com/jeremyagray/pccc/issues
Project-URL: Documentation, https://pccc.readthedocs.io/
Project-URL: Repository, https://github.com/jeremyagray/pccc
Classifier: Development Status :: 3 - Alpha
Classifier: License :: OSI Approved :: GNU General Public License v3 or later (GPLv3+)
Classifier: Intended Audience :: Developers
Classifier: Programming Language :: Python :: 3.7
Classifier: Programming Language :: Python :: 3.8
Classifier: Programming Language :: Python :: 3.9
Classifier: Programming Language :: Python :: 3.10
Classifier: Programming Language :: Python :: 3.11
Classifier: Topic :: Software Development :: Version Control :: Git
License-File: LICENSE.rst
Requires-Dist: bespon
Requires-Dist: pyenchant
Requires-Dist: pyparsing
Requires-Dist: ruamel.yaml
Requires-Dist: toml
